ultimate_hosts_blacklist/test_launcher/__init__.py
ultimate_hosts_blacklist/test_launcher/administration.py
ultimate_hosts_blacklist/test_launcher/authorization.py
ultimate_hosts_blacklist/test_launcher/cli.py
ultimate_hosts_blacklist/test_launcher/orchester.py
ultimate_hosts_blacklist/test_launcher/cleaner/__init__.py
ultimate_hosts_blacklist/test_launcher/cleaner/base.py
ultimate_hosts_blacklist/test_launcher/cleaner/infrastructure.py
ultimate_hosts_blacklist/test_launcher/data/__init__.py
ultimate_hosts_blacklist/test_launcher/data/docs/__init__.py
ultimate_hosts_blacklist/test_launcher/data/docs/about_pyfunceble.md
ultimate_hosts_blacklist/test_launcher/data/docs/about_repository.md
ultimate_hosts_blacklist/test_launcher/data/docs/about_repository_self.md
ultimate_hosts_blacklist/test_launcher/data/docs/about_ultimate.md
ultimate_hosts_blacklist/test_launcher/defaults/__init__.py
ultimate_hosts_blacklist/test_launcher/defaults/infrastructure.py
ultimate_hosts_blacklist/test_launcher/defaults/outputs.py
ultimate_hosts_blacklist/test_launcher/defaults/pyfunceble.py
ultimate_hosts_blacklist/test_launcher/pyfunceble/__init__.py
ultimate_hosts_blacklist/test_launcher/pyfunceble/producer_worker.py
ultimate_hosts_blacklist/test_launcher/pyfunceble/system_launcher.py
ultimate_hosts_blacklist/test_launcher/updater/__init__.py
ultimate_hosts_blacklist/test_launcher/updater/base.py
ultimate_hosts_blacklist/test_launcher/updater/infrastructure_files.py
ultimate_hosts_blacklist/test_launcher/updater/output_files.py
ultimate_hosts_blacklist/test_launcher/updater/readme.py
ultimate_hosts_blacklist/test_launcher/updater/requirements.py
ultimate_hosts_blacklist_test_launcher-3.0.1.dist-info/LICENSE
ultimate_hosts_blacklist_test_launcher-3.0.1.dist-info/METADATA
ultimate_hosts_blacklist_test_launcher-3.0.1.dist-info/WHEEL
ultimate_hosts_blacklist_test_launcher-3.0.1.dist-info/entry_points.txt
ultimate_hosts_blacklist_test_launcher-3.0.1.dist-info/top_level.txt
ultimate_hosts_blacklist_test_launcher-3.0.1.dist-info/RECORD
