Metadata-Version: 2.1
Name: ultimate-hosts-blacklist-test-launcher
Version: 3.0.1
Summary: The test launcher of the Ultimate-Hosts-Blacklist project.
Home-page: https://github.com/Ultimate-Hosts-Blacklist/test-launcher
License: MIT
Project-URL: Source, https://github.com/Ultimate-Hosts-Blacklist/test-launcher
Project-URL: Tracker, https://github.com/Ultimate-Hosts-Blacklist/test-launcher/issues
Keywords: Ultimate Hosts Blacklist,PyFunceble,launcher
Platform: any
Classifier: Environment :: Console
Classifier: Topic :: Internet
Classifier: Development Status :: 5 - Production/Stable
Classifier: Intended Audience :: Developers
Classifier: Programming Language :: Python
Classifier: Programming Language :: Python :: 3
Classifier: License :: OSI Approved :: MIT License
License-File: LICENSE
Requires-Dist: PyGitHub
Requires-Dist: PyFunceble-dev>=4.2.26
Requires-Dist: ultimate-hosts-blacklist-whitelist>=3.27.0
